{"generated":"2026-07-22T07:48:11.680164+00:00","window_days":90,"total_issues":420,"volume":420,"open":111,"closed":300,"shadow_chat":54,"scoreboard":{"ftr_pct":{"value":64.33333333333333,"num":193,"den":300,"target":65,"direction":"ge","verdict":"GAP"},"escalation_pct":{"value":37.61904761904762,"num":158,"den":420,"target":35,"direction":"le","verdict":"GAP"},"reopen_pct":{"value":3.3333333333333335,"num":10,"den":300,"target":5,"direction":"le","verdict":"PASS"},"sla_pct":{"value":84.33333333333333,"num":253,"den":300,"target":95,"direction":"ge","verdict":"GAP"},"response_pct":{"value":82.06388206388206,"num":334,"den":407,"target":95,"direction":"ge","verdict":"GAP"},"aged_14d":{"value":106,"num":null,"den":null,"target":0,"direction":"le","verdict":"GAP"}},"sla_detail":{"resolution_met":253,"resolution_breached":47,"response_met":334,"response_breached":73},"weekly":[{"week":"2026-04-20","n":1,"closed":1,"ftr_pct":null,"escalation_pct":null,"reopen_pct":null,"sla_pct":null,"response_pct":null},{"week":"2026-04-27","n":17,"closed":12,"ftr_pct":83.33333333333333,"escalation_pct":11.764705882352942,"reopen_pct":8.333333333333334,"sla_pct":66.66666666666667,"response_pct":88.23529411764706},{"week":"2026-05-04","n":28,"closed":20,"ftr_pct":55.0,"escalation_pct":39.285714285714285,"reopen_pct":0.0,"sla_pct":80.0,"response_pct":85.18518518518519},{"week":"2026-05-11","n":36,"closed":27,"ftr_pct":66.66666666666667,"escalation_pct":33.333333333333336,"reopen_pct":0.0,"sla_pct":81.48148148148148,"response_pct":82.85714285714286},{"week":"2026-05-18","n":58,"closed":48,"ftr_pct":72.91666666666667,"escalation_pct":29.310344827586206,"reopen_pct":2.0833333333333335,"sla_pct":81.25,"response_pct":79.3103448275862},{"week":"2026-05-25","n":70,"closed":51,"ftr_pct":60.78431372549019,"escalation_pct":44.285714285714285,"reopen_pct":1.9607843137254901,"sla_pct":94.11764705882354,"response_pct":77.61194029850746},{"week":"2026-06-01","n":56,"closed":36,"ftr_pct":50.0,"escalation_pct":48.214285714285715,"reopen_pct":0.0,"sla_pct":83.33333333333333,"response_pct":71.69811320754717},{"week":"2026-06-08","n":44,"closed":32,"ftr_pct":75.0,"escalation_pct":31.818181818181817,"reopen_pct":9.375,"sla_pct":84.375,"response_pct":88.37209302325581},{"week":"2026-06-15","n":40,"closed":27,"ftr_pct":62.96296296296296,"escalation_pct":32.5,"reopen_pct":3.7037037037037037,"sla_pct":88.88888888888889,"response_pct":82.5},{"week":"2026-06-22","n":28,"closed":19,"ftr_pct":63.1578947368421,"escalation_pct":42.857142857142854,"reopen_pct":10.526315789473685,"sla_pct":78.94736842105263,"response_pct":92.5925925925926},{"week":"2026-06-29","n":26,"closed":18,"ftr_pct":55.55555555555556,"escalation_pct":46.15384615384615,"reopen_pct":5.555555555555555,"sla_pct":83.33333333333333,"response_pct":91.66666666666667},{"week":"2026-07-06","n":10,"closed":6,"ftr_pct":null,"escalation_pct":30.0,"reopen_pct":null,"sla_pct":null,"response_pct":90.0},{"week":"2026-07-13","n":6,"closed":3,"ftr_pct":null,"escalation_pct":null,"reopen_pct":null,"sla_pct":null,"response_pct":null},{"week":"2026-07-20","n":0,"closed":0,"ftr_pct":null,"escalation_pct":null,"reopen_pct":null,"sla_pct":null,"response_pct":null}],"backlog":[{"week":"2026-04-27","open":12,"aged":0},{"week":"2026-05-04","open":20,"aged":0},{"week":"2026-05-11","open":28,"aged":5},{"week":"2026-05-18","open":41,"aged":12},{"week":"2026-05-25","open":61,"aged":20},{"week":"2026-06-01","open":74,"aged":30},{"week":"2026-06-08","open":79,"aged":46},{"week":"2026-06-15","open":97,"aged":64},{"week":"2026-06-22","open":98,"aged":75},{"week":"2026-06-29","open":106,"aged":88},{"week":"2026-07-06","open":109,"aged":96},{"week":"2026-07-13","open":111,"aged":104},{"week":"now","open":111,"aged":106}],"ftr_vs_reopen":[{"week":"2026-04-20","closed":1,"ftr_pct":null,"reopen_pct":null},{"week":"2026-04-27","closed":12,"ftr_pct":83.33333333333333,"reopen_pct":8.333333333333334},{"week":"2026-05-04","closed":20,"ftr_pct":55.0,"reopen_pct":0.0},{"week":"2026-05-11","closed":27,"ftr_pct":66.66666666666667,"reopen_pct":0.0},{"week":"2026-05-18","closed":48,"ftr_pct":72.91666666666667,"reopen_pct":2.0833333333333335},{"week":"2026-05-25","closed":51,"ftr_pct":60.78431372549019,"reopen_pct":1.9607843137254901},{"week":"2026-06-01","closed":36,"ftr_pct":50.0,"reopen_pct":0.0},{"week":"2026-06-08","closed":32,"ftr_pct":75.0,"reopen_pct":9.375},{"week":"2026-06-15","closed":27,"ftr_pct":62.96296296296296,"reopen_pct":3.7037037037037037},{"week":"2026-06-22","closed":19,"ftr_pct":63.1578947368421,"reopen_pct":10.526315789473685},{"week":"2026-06-29","closed":18,"ftr_pct":55.55555555555556,"reopen_pct":5.555555555555555},{"week":"2026-07-06","closed":6,"ftr_pct":null,"reopen_pct":null},{"week":"2026-07-13","closed":3,"ftr_pct":null,"reopen_pct":null},{"week":"2026-07-20","closed":0,"ftr_pct":null,"reopen_pct":null}],"pairing":{"r":0.5212575832906726,"weeks":10},"analysts":{"people":[{"analyst":"L. Petrov","escalated":15,"handled":30,"rate":50.0,"rateable":true,"sigma":1.8359636537137916,"outlier":false,"z":1.3998605730994327},{"analyst":"D. Fernandes","escalated":17,"handled":36,"rate":47.22222222222222,"rateable":true,"sigma":1.4263502214631771,"outlier":false,"z":1.189422574398576},{"analyst":"M. Delacroix","escalated":16,"handled":37,"rate":43.24324324324324,"rateable":true,"sigma":0.8396066563474325,"outlier":false,"z":0.7062059648921098},{"analyst":"T. Abara","escalated":16,"handled":40,"rate":40.0,"rateable":true,"sigma":0.3613552976115803,"outlier":false,"z":0.31084995334880855},{"analyst":"J. Whitfield","escalated":17,"handled":43,"rate":39.53488372093023,"rateable":true,"sigma":0.2927688624440355,"outlier":false,"z":0.25933592467983324},{"analyst":"A. Okafor","escalated":12,"handled":32,"rate":37.5,"rateable":true,"sigma":-0.0072967914139724895,"outlier":false,"z":-0.013901632529811421},{"analyst":"R. Mehta","escalated":13,"handled":37,"rate":35.13513513513514,"rateable":true,"sigma":-0.35602174049219787,"outlier":false,"z":-0.31189416756104577},{"analyst":"N. Haddad","escalated":13,"handled":38,"rate":34.21052631578947,"rateable":true,"sigma":-0.4923653296054895,"outlier":false,"z":-0.43373843912027765},{"analyst":"P. Novak","escalated":9,"handled":27,"rate":33.333333333333336,"rateable":true,"sigma":-0.6217169397898935,"outlier":false,"z":-0.45970073491114133},{"analyst":"K. Yamamoto","escalated":11,"handled":34,"rate":32.35294117647059,"rateable":true,"sigma":-0.7662863864665814,"outlier":false,"z":-0.6338685333129296},{"analyst":"C. Nkemelu","escalated":9,"handled":29,"rate":31.03448275862069,"rateable":true,"sigma":-0.9607073664800573,"outlier":false,"z":-0.731974885144906},{"analyst":"S. Lindqvist","escalated":10,"handled":37,"rate":27.027027027027028,"rateable":true,"sigma":-1.5516501373318288,"outlier":false,"z":-1.3299943000142014}],"pooled":37.61904761904762,"mean":37.54948291106433,"sd":6.7814616393689136,"lo":23.986559632326504,"hi":51.11240618980216,"floor":20,"rated":12,"excluded":[],"outliers":[],"criterion_6":"met"},"kb":{"gap":91,"escalated":158,"pct":57.59493670886076,"series":[{"week":"2026-04-20","gap":0,"escalated":0,"gap_pct":null},{"week":"2026-04-27","gap":0,"escalated":2,"gap_pct":null},{"week":"2026-05-04","gap":8,"escalated":11,"gap_pct":72.72727272727273},{"week":"2026-05-11","gap":8,"escalated":12,"gap_pct":66.66666666666667},{"week":"2026-05-18","gap":10,"escalated":17,"gap_pct":58.8235294117647},{"week":"2026-05-25","gap":16,"escalated":31,"gap_pct":51.61290322580645},{"week":"2026-06-01","gap":17,"escalated":27,"gap_pct":62.96296296296296},{"week":"2026-06-08","gap":6,"escalated":14,"gap_pct":42.857142857142854},{"week":"2026-06-15","gap":7,"escalated":13,"gap_pct":53.84615384615385},{"week":"2026-06-22","gap":6,"escalated":12,"gap_pct":50.0},{"week":"2026-06-29","gap":10,"escalated":12,"gap_pct":83.33333333333333},{"week":"2026-07-06","gap":2,"escalated":3,"gap_pct":null},{"week":"2026-07-13","gap":1,"escalated":4,"gap_pct":null},{"week":"2026-07-20","gap":0,"escalated":0,"gap_pct":null}],"by_tower":[["End User Computing",26],["Enterprise Applications",26],["Network & Connectivity",16],["Cloud & Security",10],["Compute & Storage",8],["Database",5]],"by_reason":[["Root cause unclear after triage",24],["Requires elevated access",17],["Suspected platform defect",15],["Vendor engagement required",14],["Change required to resolve",11],["Beyond documented runbook",10]]},"towers":[{"tower":"End User Computing","volume":126,"closed":90,"ftr_pct":66.66666666666667,"escalation_pct":37.301587301587304,"sla_pct":84.44444444444444,"aged":34,"open":35,"known":true,"pilot_score":4199.999999999999,"pilot_rank":2},{"tower":"Enterprise Applications","volume":101,"closed":62,"ftr_pct":54.83870967741935,"escalation_pct":44.554455445544555,"sla_pct":85.48387096774194,"aged":32,"open":34,"known":true,"pilot_score":4561.290322580646,"pilot_rank":1},{"tower":"Network & Connectivity","volume":63,"closed":45,"ftr_pct":62.22222222222222,"escalation_pct":36.507936507936506,"sla_pct":80.0,"aged":16,"open":16,"known":true,"pilot_score":2380.0,"pilot_rank":3},{"tower":"Database","volume":46,"closed":39,"ftr_pct":71.7948717948718,"escalation_pct":30.434782608695652,"sla_pct":82.05128205128206,"aged":7,"open":7,"known":true,"pilot_score":1297.4358974358975,"pilot_rank":6},{"tower":"Compute & Storage","volume":46,"closed":36,"ftr_pct":69.44444444444444,"escalation_pct":30.434782608695652,"sla_pct":91.66666666666667,"aged":8,"open":10,"known":true,"pilot_score":1405.5555555555557,"pilot_rank":4},{"tower":"Cloud & Security","volume":38,"closed":28,"ftr_pct":64.28571428571429,"escalation_pct":39.473684210526315,"sla_pct":82.14285714285714,"aged":9,"open":9,"known":true,"pilot_score":1357.1428571428569,"pilot_rank":5}],"intake":[{"channel":"Portal","n":199,"pct":47.38095238095238,"shadow":false},{"channel":"Email","n":104,"pct":24.761904761904763,"shadow":false},{"channel":"Monitoring","n":63,"pct":15.0,"shadow":false},{"channel":"Chat","n":54,"pct":12.857142857142858,"shadow":true}],"channel_quality":[{"channel":"Portal","n":199,"ftr_pct":63.38028169014085,"escalation_pct":39.698492462311556},{"channel":"Email","n":104,"ftr_pct":61.19402985074627,"escalation_pct":38.46153846153846},{"channel":"Monitoring","n":63,"ftr_pct":69.38775510204081,"escalation_pct":33.333333333333336},{"channel":"Chat","n":54,"ftr_pct":66.66666666666667,"escalation_pct":33.333333333333336}],"ageing":{"buckets":[{"label":"0-3d","lo":0,"hi":3,"n":0,"breach":false},{"label":"3-7d","lo":3,"hi":7,"n":1,"breach":false},{"label":"7-14d","lo":7,"hi":14,"n":4,"breach":false},{"label":"14-30d","lo":14,"hi":30,"n":18,"breach":true},{"label":"30-60d","lo":30,"hi":60,"n":58,"breach":true},{"label":"60d+","lo":60,"hi":null,"n":30,"breach":true}],"total":111,"oldest":83.24457963152778,"median":47.645274075972225,"over_30":88},"ageing_by_status":{"buckets":[{"label":"0-3d","owned":0,"paused":0},{"label":"3-7d","owned":1,"paused":0},{"label":"7-14d","owned":4,"paused":0},{"label":"14-30d","owned":18,"paused":0},{"label":"30-60d","owned":58,"paused":0},{"label":"60d+","owned":30,"paused":0}],"paused_total":0,"owned_total":111,"by_status":[["Escalated to L2",30],["Waiting for approval",25],["Pending",21],["Open",7],["Work in progress",7],["In Progress",5],["Waiting for support",5],["Awaiting CAB approval",4],["Escalated",4],["Waiting for customer",2],["Implementing",1]]},"invariants":[],"weekly_sums":[],"jira_time_counterexample":{"created_distinct_dates":1,"resolutiondate_distinct_dates":1},"project":"ITSM","site":"https://singhaditya21.atlassian.net","pages":5,"warnings":["field 'Urgency' is ambiguous on this instance: using customfield_10044, ignoring customfield_10071 (its JQL will use the cf[] form). Pin it with JIRA_FIELD_ID__URGENCY=<id> to be explicit."],"chat_weekly":[{"week":"2026-04-20","n":0},{"week":"2026-04-27","n":2},{"week":"2026-05-04","n":4},{"week":"2026-05-11","n":6},{"week":"2026-05-18","n":4},{"week":"2026-05-25","n":10},{"week":"2026-06-01","n":9},{"week":"2026-06-08","n":5},{"week":"2026-06-15","n":5},{"week":"2026-06-22","n":5},{"week":"2026-06-29","n":1},{"week":"2026-07-06","n":3},{"week":"2026-07-13","n":0},{"week":"2026-07-20","n":0}],"generated_label":"22 Jul 2026 13:18 UTC+05:30","window_label":"20 Apr \u2013 22 Jul 2026","generated_at":"2026-07-22T07:48:06.415613+00:00","now_ts":1784706491.680164,"window_start_ts":1776930491.680164}